datamanipulation/__init__.py
datamanipulation/datafetcher.py
stockdatamanipulation-0.1.1.dist-info/LICENSE
stockdatamanipulation-0.1.1.dist-info/METADATA
stockdatamanipulation-0.1.1.dist-info/WHEEL
stockdatamanipulation-0.1.1.dist-info/top_level.txt
stockdatamanipulation-0.1.1.dist-info/RECORD
